[
  {
    "category": "КОНУСНО-ЛУЧЕВАЯ КОМПЬЮТЕРНАЯ ТОМОГРАФИЯ",
    "name": "КЛКТ 16х14 см(2 челюсти + верхнечелюстные синусы + ВНЧС)",
    "price": "3900"
  },
  {
    "category": "КОНУСНО-ЛУЧЕВАЯ КОМПЬЮТЕРНАЯ ТОМОГРАФИЯ",
    "name": "КЛКТ 16х8см(2 челюсти + нижние отделы верхнечелюстных синусов)",
    "price": "3700"
  },
  {
    "category": "КОНУСНО-ЛУЧЕВАЯ КОМПЬЮТЕРНАЯ ТОМОГРАФИЯ",
    "name": "КЛКТ 16х5 см (1 челюсть)",
    "price": "2900"
  },
  {
    "category": "ИССЛЕДОВАНИЕ ВИСОЧНО-НИЖНЕЧЕЛЮСТНЫХ СУСТАВОВ",
    "name": "КЛКТ одного ВНЧС (8х8см, в одной позиции)",
    "price": "1300"
  },
  {
    "category": "ИССЛЕДОВАНИЕ ВИСОЧНО-НИЖНЕЧЕЛЮСТНЫХ СУСТАВОВ",
    "name": "КЛКТ одного ВНЧС (8х8см, в двух позициях)",
    "price": "2400"
  },
  {
    "category": "ИССЛЕДОВАНИЕ ВИСОЧНО-НИЖНЕЧЕЛЮСТНЫХ СУСТАВОВ",
    "name": "КЛКТ двух ВНЧС (16х8см или 16х14см, в одной позиции)",
    "price": "4000"
  },
  {
    "category": "ИССЛЕДОВАНИЕ ЛОР-ОРГАНОВ",
    "name": "КЛКТ верхнечелюстных синусов",
    "price": "3200"
  },
  {
    "category": "ИССЛЕДОВАНИЕ ЛОР-ОРГАНОВ",
    "name": "КЛКТ верхнечелюстных, решетчатых и клиновидных синусов",
    "price": "3650"
  },
  {
    "category": "ИССЛЕДОВАНИЕ ЛОР-ОРГАНОВ",
    "name": "КЛКТ всех околоносовых синусов",
    "price": "4500"
  },
  {
    "category": "ОРТОПАНТОМОГРАФИЯ",
    "name": "Цифровая",
    "price": "1300"
  },
  {
    "category": "ОРТОПАНТОМОГРАФИЯ",
    "name": "Реконструкция из КЛКТ",
    "price": "1300"
  },
  {
    "category": "ОРТОПАНТОМОГРАФИЯ",
    "name": "Описание ОПТГ",
    "price": "1500"
  },
  {
    "category": "ТЕЛЕРЕНТГЕНОГРАФИЯ",
    "name": "Цифровая ТРГ (одна проекция)",
    "price": "1300"
  },
  {
    "category": "ТЕЛЕРЕНТГЕНОГРАФИЯ",
    "name": "Цифровая ТРГ (две проекции)",
    "price": "2000"
  },
  {
    "category": "ТЕЛЕРЕНТГЕНОГРАФИЯ",
    "name": "Расчет телерентгенограммы",
    "price": "2200"
  },
  {
    "category": "ДОПОЛНИТЕЛЬНЫЕ УСЛУГИ",
    "name": "Доставка курьером по Москве",
    "price": "400"
  },
  {
    "category": "ДОПОЛНИТЕЛЬНЫЕ УСЛУГИ",
    "name": "Доставка курьером в ближнее Подмосковье",
    "price": "600"
  },
  {
    "category": "ДОПОЛНИТЕЛЬНЫЕ УСЛУГИ",
    "name": "Дублирование исследования на пленке",
    "price": "400"
  },
  {
    "category": "КОМПЛЕКСНЫЕ ПРЕДЛОЖЕНИЯ",
    "name": "«Терапевт» (ОПТГ цифровая + КЛКТ 4х5см (К-06+))",
    "price": "3200"
  },
  {
    "category": "КОМПЛЕКСНЫЕ ПРЕДЛОЖЕНИЯ",
    "name": "«Имплантолог» (ОПТГ + КЛКТ 8х8см)",
    "price": "3800"
  },
  {
    "category": "КОМПЛЕКСНЫЕ ПРЕДЛОЖЕНИЯ",
    "name": "«Ортодонт» (ОПТГ+ТРГ+ расчет ТРГ)",
    "price": "4200"
  }
]